{
  "format_version": "1.16.100",
  "minecraft:fog_settings": {
    "description": {
      "identifier": "jgrtx:basalt_deltas"
    },
    "distance": {
      "air": {
        "fog_start": 11.11,
        "fog_end": 96.666,
        "fog_color": "#705f6f",
        "render_distance_type": "fixed"
      },
      "water": {
        "fog_start": 0.0,
        "fog_end": 15.5,
        "fog_color": "#353135",
        "render_distance_type": "fixed"
      },
      "weather": {
        "fog_start": 9.999,
        "fog_end": 96.666,
        "fog_color": "#6b636b",
        "render_distance_type": "fixed"
      }
    },
    "volumetric": {
      "density": {
        "air": {
          "max_density": 0.0025,
          "uniform": true
        },
        "lava": {
          "max_density": 0.125,
          "uniform": true
        }
      },
      "media_coefficients": {
        "air": {
          "absorption": [0.0, 0.2, 0.19],
          "scattering": [0.2, 0.01, 0.015]
        }
      }
    }
  }
}
